Metadata-Version: 2.1
Name: Data-Studio
Version: 2.0
Summary: Data Studio annotation tool
Home-page: https://github.com/LabelStudio-IndikaAI/label-studio.git
Author: Heartex
Author-email: Data@indikaai.com
License: UNKNOWN
Platform: UNKNOWN
Classifier: Programming Language :: Python :: 3
Classifier: License :: OSI Approved :: Apache Software License
Classifier: Operating System :: OS Independent
Requires-Python: >=3.6
License-File: LICENSE
License-File: NOTICE
Requires-Dist: Django (==3.2.20)
Requires-Dist: appdirs (>=1.4.3)
Requires-Dist: attr (==0.3.1)
Requires-Dist: attrs (>=19.2.0)
Requires-Dist: azure-storage-blob (>=12.6.0)
Requires-Dist: bleach (~=5.0.0)
Requires-Dist: boto3 (~=1.16.28)
Requires-Dist: botocore (~=1.19.28)
Requires-Dist: boto (~=2.49.0)
Requires-Dist: boxing (>=0.1.4)
Requires-Dist: colorama (>=0.4.4)
Requires-Dist: defusedxml (>=0.7.1)
Requires-Dist: django-cors-headers (==3.6.0)
Requires-Dist: django-environ (==0.10.0)
Requires-Dist: django-extensions (==3.1.0)
Requires-Dist: django-ranged-fileresponse (>=0.1.2)
Requires-Dist: django-rest-swagger (==2.2.0)
Requires-Dist: django-storages (==1.12.3)
Requires-Dist: django-user-agents (==0.4.0)
Requires-Dist: django-annoying (==0.10.6)
Requires-Dist: django-debug-toolbar (==3.2.1)
Requires-Dist: django-filter (==2.4.0)
Requires-Dist: django-model-utils (==4.1.1)
Requires-Dist: django-rq (==2.5.1)
Requires-Dist: djangorestframework (==3.13.1)
Requires-Dist: drf-flex-fields (==0.9.5)
Requires-Dist: drf-generators (==0.3.0)
Requires-Dist: drf-dynamic-fields (==0.3.0)
Requires-Dist: drf-yasg (==1.20.0)
Requires-Dist: google-api-core (==2.11.0)
Requires-Dist: google-auth (==2.14.1)
Requires-Dist: google-cloud-appengine-logging (==1.1.0)
Requires-Dist: google-cloud-audit-log (==0.2.0)
Requires-Dist: google-cloud-core (==2.3.2)
Requires-Dist: google-cloud-logging (~=2.7.0)
Requires-Dist: google-cloud-storage (~=2.5.0)
Requires-Dist: google-resumable-media (==2.3.3)
Requires-Dist: googleapis-common-protos (==1.56.4)
Requires-Dist: grpc-google-iam-v1 (==0.12.4)
Requires-Dist: htmlmin (==0.1.12)
Requires-Dist: jsonschema (==3.2.0)
Requires-Dist: label-studio-converter (==0.0.55)
Requires-Dist: launchdarkly-server-sdk (==7.5.0)
Requires-Dist: lockfile (>=0.12.0)
Requires-Dist: lxml (>=4.2.5)
Requires-Dist: numpy (==1.24.3)
Requires-Dist: ordered-set (==4.0.2)
Requires-Dist: pandas (>=0.24.0)
Requires-Dist: protobuf (>=3.15.5)
Requires-Dist: psycopg2-binary (==2.9.6)
Requires-Dist: pydantic (<=1.11.0,>=1.7.3)
Requires-Dist: python-json-logger (==2.0.4)
Requires-Dist: python-dateutil (==2.8.1)
Requires-Dist: pytz (~=2022.1)
Requires-Dist: pyyaml (>=5.3.1)
Requires-Dist: redis (~=3.5)
Requires-Dist: requests (==2.31.0)
Requires-Dist: rq (==1.10.1)
Requires-Dist: rules (==2.2)
Requires-Dist: sentry-sdk (>=1.1.0)
Requires-Dist: ujson (>=3.0.0)
Requires-Dist: urllib3 (==1.26.16)
Requires-Dist: wheel (<=0.40.0,>=0.38.1)
Requires-Dist: xmljson (==0.2.0)
Provides-Extra: mysql
Requires-Dist: mysqlclient ; extra == 'mysql'
